MANIFEST.in
README.txt
plonetheme.terrafirma-configure.zcml
setup.cfg
setup.py
docs/HISTORY.txt
docs/INSTALL.txt
docs/LICENSE.GPL
docs/LICENSE.txt
plonetheme/__init__.py
plonetheme.terrafirma.egg-info/PKG-INFO
plonetheme.terrafirma.egg-info/SOURCES.txt
plonetheme.terrafirma.egg-info/dependency_links.txt
plonetheme.terrafirma.egg-info/entry_points.txt
plonetheme.terrafirma.egg-info/namespace_packages.txt
plonetheme.terrafirma.egg-info/not-zip-safe
plonetheme.terrafirma.egg-info/paster_plugins.txt
plonetheme.terrafirma.egg-info/requires.txt
plonetheme.terrafirma.egg-info/top_level.txt
plonetheme/terrafirma/.DS_Store
plonetheme/terrafirma/README.txt
plonetheme/terrafirma/__init__.py
plonetheme/terrafirma/configure.zcml
plonetheme/terrafirma/portlets.xml
plonetheme/terrafirma/profiles.zcml
plonetheme/terrafirma/setuphandlers.py
plonetheme/terrafirma/skins.zcml
plonetheme/terrafirma/version.txt
plonetheme/terrafirma/browser/__init__.py
plonetheme/terrafirma/browser/author_link.pt
plonetheme/terrafirma/browser/author_link.py
plonetheme/terrafirma/browser/configure.zcml
plonetheme/terrafirma/browser/interfaces.py
plonetheme/terrafirma/browser/logo.pt
plonetheme/terrafirma/browser/logo.py
plonetheme/terrafirma/profiles/default/cssregistry.xml
plonetheme/terrafirma/profiles/default/import_steps.xml
plonetheme/terrafirma/profiles/default/jsregistry.xml
plonetheme/terrafirma/profiles/default/metadata.xml
plonetheme/terrafirma/profiles/default/plonetheme.terrafirma_various.txt
plonetheme/terrafirma/profiles/default/skins.xml
plonetheme/terrafirma/profiles/default/viewlets.xml
plonetheme/terrafirma/skins/.DS_Store
plonetheme/terrafirma/skins/plonetheme_terrafirma_custom_images/CONTENT.txt
plonetheme/terrafirma/skins/plonetheme_terrafirma_custom_images/a1.gif
plonetheme/terrafirma/skins/plonetheme_terrafirma_custom_images/a10.jpg
plonetheme/terrafirma/skins/plonetheme_terrafirma_custom_images/a16.gif
plonetheme/terrafirma/skins/plonetheme_terrafirma_custom_images/a18.gif
plonetheme/terrafirma/skins/plonetheme_terrafirma_custom_images/a22.gif
plonetheme/terrafirma/skins/plonetheme_terrafirma_custom_images/a26.gif
plonetheme/terrafirma/skins/plonetheme_terrafirma_custom_images/a33.gif
plonetheme/terrafirma/skins/plonetheme_terrafirma_custom_images/a36.gif
plonetheme/terrafirma/skins/plonetheme_terrafirma_custom_images/a38.gif
