Metadata-Version: 1.0
Name: plonetheme.terrafirma
Version: 0.3
Summary: An installable theme for Plone 3.0
Home-page: http://svn.plone.org/svn/collective/plonetheme.terrafirma
Author: Aleksandr Vladimirskiy
Author-email: sasha@theotheralex.com
License: GPL
Keywords: web zope plone theme
Platform: UNKNOWN
Classifier: Framework :: Plone
Classifier: Programming Language :: Python
Classifier: Topic :: Software Development :: Libraries :: Python Modules
